running_process/__init__.py
running_process/line_iterator.py
running_process/output_formatter.py
running_process/process_output_reader.py
running_process/process_utils.py
running_process/process_watcher.py
running_process/pty.py
running_process/running_process.py
running_process/running_process_manager.py
running_process/subprocess_runner.py
running_process/assets/example.txt
running_process-1.0.7.dist-info/METADATA
running_process-1.0.7.dist-info/WHEEL
running_process-1.0.7.dist-info/licenses/LICENSE
running_process-1.0.7.dist-info/RECORD
