Metadata-Version: 2.4
Name: running_process
Version: 1.0.7
Summary: A modern subprocess.Popen wrapper with improved process management
Project-URL: Homepage, https://github.com/yourusername/running-process
Project-URL: Repository, https://github.com/yourusername/running-process
Project-URL: Issues, https://github.com/yourusername/running-process/issues
Author-email: Your Name <your.email@example.com>
License: BSD 3-Clause License
License-File: LICENSE
Keywords: cli,management,process,subprocess
Classifier: Development Status :: 5 - Production/Stable
Classifier: Intended Audience :: Developers
Classifier: License :: OSI Approved :: BSD License
Classifier: Operating System :: OS Independent
Classifier: Programming Language :: Python :: 3
Classifier: Programming Language :: Python :: 3.10
Classifier: Programming Language :: Python :: 3.11
Classifier: Programming Language :: Python :: 3.12
Classifier: Programming Language :: Python :: 3.13
Classifier: Topic :: Software Development :: Libraries :: Python Modules
Classifier: Topic :: System :: System Shells
Classifier: Typing :: Typed
Requires-Python: >=3.10
Requires-Dist: psutil>=5.9.0
Requires-Dist: typing-extensions>=4.8.0; python_version < '3.11'
Provides-Extra: dev
Requires-Dist: black>=24.0.0; extra == 'dev'
Requires-Dist: isort>=5.13.0; extra == 'dev'
Requires-Dist: pyright>=1.1.0; extra == 'dev'
Requires-Dist: pytest-cov>=5.0.0; extra == 'dev'
Requires-Dist: pytest-xdist>=3.5.0; extra == 'dev'
Requires-Dist: pytest>=8.0.0; extra == 'dev'
Requires-Dist: ruff>=0.8.0; extra == 'dev'
Provides-Extra: test
Requires-Dist: pytest-cov>=5.0.0; extra == 'test'
Requires-Dist: pytest-xdist>=3.5.0; extra == 'test'
Requires-Dist: pytest>=8.0.0; extra == 'test'
